{
  "default_pixels": 4,
  "color_format": "rgb",
  "refresh_rate": 100,
  "end_time": 12995,
  "sequence": {
    "0": {
      "color": [
        0,
        0,
        0
      ],
      "pixels": 4
    },
    "1070": {
      "color": [
        255,
        0,
        0
      ],
      "pixels": 4
    },
    "1103": {
      "color": [
        0,
        0,
        0
      ],
      "pixels": 4
    },
    "1279": {
      "color": [
        255,
        0,
        0
      ],
      "pixels": 4
    },
    "1287": {
      "color": [
        0,
        0,
        0
      ],
      "pixels": 4
    },
    "2170": {
      "color": [
        255,
        0,
        0
      ],
      "pixels": 4
    },
    "2186": {
      "color": [
        0,
        0,
        0
      ],
      "pixels": 4
    },
    "2821": {
      "color": [
        255,
        0,
        0
      ],
      "pixels": 4
    },
    "2831": {
      "color": [
        0,
        0,
        0
      ],
      "pixels": 4
    },
    "3329": {
      "color": [
        255,
        0,
        0
      ],
      "pixels": 4
    },
    "3347": {
      "color": [
        0,
        0,
        0
      ],
      "pixels": 4
    },
    "4455": {
      "color": [
        255,
        0,
        0
      ],
      "pixels": 4
    },
    "4475": {
      "color": [
        0,
        0,
        0
      ],
      "pixels": 4
    },
    "5589": {
      "color": [
        255,
        0,
        0
      ],
      "pixels": 4
    },
    "5618": {
      "color": [
        0,
        0,
        0
      ],
      "pixels": 4
    },
    "5722": {
      "color": [
        255,
        0,
        0
      ],
      "pixels": 4
    },
    "5725": {
      "color": [
        0,
        0,
        0
      ],
      "pixels": 4
    },
    "6149": {
      "color": [
        255,
        0,
        0
      ],
      "pixels": 4
    },
    "6167": {
      "color": [
        0,
        0,
        0
      ],
      "pixels": 4
    },
    "6717": {
      "color": [
        255,
        0,
        0
      ],
      "pixels": 4
    },
    "6731": {
      "color": [
        0,
        0,
        0
      ],
      "pixels": 4
    },
    "10105": {
      "color": [
        255,
        0,
        0
      ],
      "pixels": 4
    },
    "10136": {
      "color": [
        0,
        0,
        0
      ],
      "pixels": 4
    },
    "11521": {
      "color": [
        255,
        0,
        0
      ],
      "pixels": 4
    },
    "11550": {
      "color": [
        0,
        0,
        0
      ],
      "pixels": 4
    },
    "12185": {
      "color": [
        255,
        0,
        0
      ],
      "pixels": 4
    },
    "12193": {
      "color": [
        0,
        0,
        0
      ],
      "pixels": 4
    },
    "12325": {
      "color": [
        255,
        0,
        0
      ],
      "pixels": 4
    },
    "12327": {
      "color": [
        0,
        0,
        0
      ],
      "pixels": 4
    },
    "12360": {
      "color": [
        255,
        0,
        0
      ],
      "pixels": 4
    },
    "12395": {
      "color": [
        0,
        0,
        0
      ],
      "pixels": 4
    },
    "12919": {
      "color": [
        255,
        0,
        0
      ],
      "pixels": 4
    },
    "12943": {
      "color": [
        0,
        0,
        0
      ],
      "pixels": 4
    }
  }
}